hello_world_20250130/__init__.py
hello_world_20250130/main.py
hello_world_20250130-0.1.1.dist-info/METADATA
hello_world_20250130-0.1.1.dist-info/WHEEL
hello_world_20250130-0.1.1.dist-info/RECORD
